mkpod.py
mkpod-1.0.15.dist-info/METADATA
mkpod-1.0.15.dist-info/WHEEL
mkpod-1.0.15.dist-info/RECORD
