Metadata-Version: 2.4
Name: mkpod
Version: 1.0.15
Summary: A Package designed to use containers with a Mikrotik RDS/Rose Appliance
Project-URL: Homepage, https://https://github.com/glennswest/mkpod
Project-URL: Issues, https://https://github.com/glennswest/mkpod/issues
Author-email: glenn west <glennswest@neuralcloudcomputing.com>
License-Expression: MIT
Classifier: Operating System :: OS Independent
Classifier: Programming Language :: Python :: 3
Requires-Python: >=3.9
Requires-Dist: annotated-types==0.7.0
Requires-Dist: backports-tarfile==1.2.0
Requires-Dist: bcrypt==4.3.0
Requires-Dist: cffi==1.17.1
Requires-Dist: cryptography==44.0.3
Requires-Dist: datetime==5.5
Requires-Dist: decorator==5.2.1
Requires-Dist: fabric==3.2.2
Requires-Dist: invoke==2.2.0
Requires-Dist: keyring==25.6.0
Requires-Dist: more-itertools==10.7.0
Requires-Dist: paramiko==3.5.1
Requires-Dist: psycopg2==2.9.10
Requires-Dist: pycparser==2.22
Requires-Dist: pydantic-core==2.33.1
Requires-Dist: pydantic==2.11.3
Requires-Dist: pygments==2.19.1
Requires-Dist: pynacl==1.5.0
Requires-Dist: pytz==2025.2
Requires-Dist: rich==14.0.0
Requires-Dist: tomli==2.2.1
